{
    "swagger": "2.0",
    "info": {
        "description": "RESTful API for E-Wallet Application",
        "title": "Wallet API",
        "contact": {},
        "version": "1.0"
    },
    "host": "localhost:3000",
    "basePath": "/api",
    "paths": {
        "/auth/login": {
            "post": {
                "description": "Login with email and password to receive JWT token",
                "consumes": [
                    "application/json"
                ],
                "produces": [
                    "application/json"
                ],
                "tags": [
                    "Auth"
                ],
                "summary": "Login user",
                "parameters": [
                    {
                        "description": "Login Request",
                        "name": "request",
                        "in": "body",
                        "required": true,
                        "schema": {
                            "$ref": "#/definitions/handler.LoginRequest"
                        }
                    }
                ],
                "responses": {
                    "200": {
                        "description": "OK",
                        "schema": {
                            "type": "object",
                            "additionalProperties": {
                                "type": "string"
                            }
                        }
                    },
                    "400": {
                        "description": "Bad Request",
                        "schema": {
                            "$ref": "#/definitions/utils.ApiResponse"
                        }
                    },
                    "401": {
                        "description": "Unauthorized",
                        "schema": {
                            "$ref": "#/definitions/utils.ApiResponse"
                        }
                    },
                    "500": {
                        "description": "Internal Server Error",
                        "schema": {
                            "$ref": "#/definitions/utils.ApiResponse"
                        }
                    }
                }
            }
        },
        "/auth/register": {
            "post": {
                "description": "Register a new user with name, email, and password",
                "consumes": [
                    "application/json"
                ],
                "produces": [
                    "application/json"
                ],
                "tags": [
                    "Auth"
                ],
                "summary": "Register a new user",
                "parameters": [
                    {
                        "description": "Register Request",
                        "name": "request",
                        "in": "body",
                        "required": true,
                        "schema": {
                            "$ref": "#/definitions/handler.RegisterRequest"
                        }
                    }
                ],
                "responses": {
                    "201": {
                        "description": "Created",
                        "schema": {
                            "type": "object",
                            "additionalProperties": {
                                "type": "string"
                            }
                        }
                    },
                    "400": {
                        "description": "Bad Request",
                        "schema": {
                            "$ref": "#/definitions/utils.ApiResponse"
                        }
                    },
                    "409": {
                        "description": "Conflict",
                        "schema": {
                            "$ref": "#/definitions/utils.ApiResponse"
                        }
                    },
                    "500": {
                        "description": "Internal Server Error",
                        "schema": {
                            "$ref": "#/definitions/utils.ApiResponse"
                        }
                    }
                }
            }
        },
        "/transactions/history": {
            "get": {
                "security": [
                    {
                        "BearerAuth": []
                    }
                ],
                "description": "Get transaction history for logged-in user with pagination",
                "consumes": [
                    "application/json"
                ],
                "produces": [
                    "application/json"
                ],
                "tags": [
                    "Wallet"
                ],
                "summary": "Get transaction history",
                "parameters": [
                    {
                        "type": "integer",
                        "description": "Page number",
                        "name": "page",
                        "in": "query"
                    },
                    {
                        "type": "integer",
                        "description": "Items per page",
                        "name": "limit",
                        "in": "query"
                    }
                ],
                "responses": {
                    "200": {
                        "description": "OK",
                        "schema": {
                            "allOf": [
                                {
                                    "$ref": "#/definitions/utils.ApiResponse"
                                },
                                {
                                    "type": "object",
                                    "properties": {
                                        "data": {
                                            "type": "array",
                                            "items": {
                                                "$ref": "#/definitions/domain.Transaction"
                                            }
                                        }
                                    }
                                }
                            ]
                        }
                    },
                    "401": {
                        "description": "Unauthorized",
                        "schema": {
                            "$ref": "#/definitions/utils.ApiResponse"
                        }
                    },
                    "500": {
                        "description": "Internal Server Error",
                        "schema": {
                            "$ref": "#/definitions/utils.ApiResponse"
                        }
                    }
                }
            }
        },
        "/transactions/transfer": {
            "post": {
                "security": [
                    {
                        "BearerAuth": []
                    }
                ],
                "description": "Transfer funds from logged-in user to another user",
                "consumes": [
                    "application/json"
                ],
                "produces": [
                    "application/json"
                ],
                "tags": [
                    "Wallet"
                ],
                "summary": "Transfer funds",
                "parameters": [
                    {
                        "description": "Transfer Request",
                        "name": "request",
                        "in": "body",
                        "required": true,
                        "schema": {
                            "$ref": "#/definitions/handler.TransferRequest"
                        }
                    }
                ],
                "responses": {
                    "200": {
                        "description": "OK",
                        "schema": {
                            "allOf": [
                                {
                                    "$ref": "#/definitions/utils.ApiResponse"
                                },
                                {
                                    "type": "object",
                                    "properties": {
                                        "data": {
                                            "$ref": "#/definitions/domain.Transaction"
                                        }
                                    }
                                }
                            ]
                        }
                    },
                    "400": {
                        "description": "Bad Request",
                        "schema": {
                            "$ref": "#/definitions/utils.ApiResponse"
                        }
                    },
                    "401": {
                        "description": "Unauthorized",
                        "schema": {
                            "$ref": "#/definitions/utils.ApiResponse"
                        }
                    }
                }
            }
        },
        "/users/profile": {
            "get": {
                "security": [
                    {
                        "BearerAuth": []
                    }
                ],
                "description": "Get the profile of the logged-in user",
                "consumes": [
                    "application/json"
                ],
                "produces": [
                    "application/json"
                ],
                "tags": [
                    "User"
                ],
                "summary": "Get user profile",
                "responses": {
                    "200": {
                        "description": "OK",
                        "schema": {
                            "allOf": [
                                {
                                    "$ref": "#/definitions/utils.ApiResponse"
                                },
                                {
                                    "type": "object",
                                    "properties": {
                                        "data": {
                                            "$ref": "#/definitions/domain.User"
                                        }
                                    }
                                }
                            ]
                        }
                    },
                    "401": {
                        "description": "Unauthorized",
                        "schema": {
                            "$ref": "#/definitions/utils.ApiResponse"
                        }
                    },
                    "404": {
                        "description": "Not Found",
                        "schema": {
                            "$ref": "#/definitions/utils.ApiResponse"
                        }
                    },
                    "500": {
                        "description": "Internal Server Error",
                        "schema": {
                            "$ref": "#/definitions/utils.ApiResponse"
                        }
                    }
                }
            }
        },
        "/wallets/balance": {
            "get": {
                "security": [
                    {
                        "BearerAuth": []
                    }
                ],
                "description": "Get current balance of logged-in user",
                "consumes": [
                    "application/json"
                ],
                "produces": [
                    "application/json"
                ],
                "tags": [
                    "Wallet"
                ],
                "summary": "Get user balance",
                "responses": {
                    "200": {
                        "description": "OK",
                        "schema": {
                            "allOf": [
                                {
                                    "$ref": "#/definitions/utils.ApiResponse"
                                },
                                {
                                    "type": "object",
                                    "properties": {
                                        "data": {
                                            "$ref": "#/definitions/domain.Wallet"
                                        }
                                    }
                                }
                            ]
                        }
                    },
                    "401": {
                        "description": "Unauthorized",
                        "schema": {
                            "$ref": "#/definitions/utils.ApiResponse"
                        }
                    },
                    "404": {
                        "description": "Not Found",
                        "schema": {
                            "$ref": "#/definitions/utils.ApiResponse"
                        }
                    },
                    "500": {
                        "description": "Internal Server Error",
                        "schema": {
                            "$ref": "#/definitions/utils.ApiResponse"
                        }
                    }
                }
            }
        },
        "/wallets/topup": {
            "post": {
                "security": [
                    {
                        "BearerAuth": []
                    }
                ],
                "description": "Top up wallet balance for logged-in user",
                "consumes": [
                    "application/json"
                ],
                "produces": [
                    "application/json"
                ],
                "tags": [
                    "Wallet"
                ],
                "summary": "Top up wallet",
                "parameters": [
                    {
                        "description": "TopUp Request",
                        "name": "request",
                        "in": "body",
                        "required": true,
                        "schema": {
                            "$ref": "#/definitions/handler.TopUpRequest"
                        }
                    }
                ],
                "responses": {
                    "200": {
                        "description": "OK",
                        "schema": {
                            "allOf": [
                                {
                                    "$ref": "#/definitions/utils.ApiResponse"
                                },
                                {
                                    "type": "object",
                                    "properties": {
                                        "data": {
                                            "$ref": "#/definitions/domain.Wallet"
                                        }
                                    }
                                }
                            ]
                        }
                    },
                    "400": {
                        "description": "Bad Request",
                        "schema": {
                            "$ref": "#/definitions/utils.ApiResponse"
                        }
                    },
                    "401": {
                        "description": "Unauthorized",
                        "schema": {
                            "$ref": "#/definitions/utils.ApiResponse"
                        }
                    },
                    "500": {
                        "description": "Internal Server Error",
                        "schema": {
                            "$ref": "#/definitions/utils.ApiResponse"
                        }
                    }
                }
            }
        }
    },
    "definitions": {
        "domain.Transaction": {
            "type": "object",
            "required": [
                "amount"
            ],
            "properties": {
                "amount": {
                    "type": "number"
                },
                "created_at": {
                    "type": "string"
                },
                "id": {
                    "type": "integer"
                },
                "receiver_wallet_id": {
                    "description": "Nullable if withdrawing to external",
                    "type": "integer"
                },
                "sender_wallet_id": {
                    "description": "Nullable if system sends money",
                    "type": "integer"
                },
                "status": {
                    "$ref": "#/definitions/domain.TransactionStatus"
                },
                "updated_at": {
                    "type": "string"
                }
            }
        },
        "domain.TransactionStatus": {
            "type": "string",
            "enum": [
                "pending",
                "success",
                "failed"
            ],
            "x-enum-varnames": [
                "TransactionStatusPending",
                "TransactionStatusSuccess",
                "TransactionStatusFailed"
            ]
        },
        "domain.User": {
            "type": "object",
            "required": [
                "email",
                "name",
                "password"
            ],
            "properties": {
                "created_at": {
                    "type": "string"
                },
                "email": {
                    "type": "string"
                },
                "id": {
                    "type": "integer"
                },
                "name": {
                    "type": "string"
                },
                "password": {
                    "type": "string",
                    "minLength": 6
                },
                "updated_at": {
                    "type": "string"
                }
            }
        },
        "domain.Wallet": {
            "type": "object",
            "required": [
                "user_id"
            ],
            "properties": {
                "balance": {
                    "type": "number"
                },
                "created_at": {
                    "type": "string"
                },
                "id": {
                    "type": "integer"
                },
                "updated_at": {
                    "type": "string"
                },
                "user_id": {
                    "type": "integer"
                }
            }
        },
        "handler.LoginRequest": {
            "type": "object",
            "required": [
                "email",
                "password"
            ],
            "properties": {
                "email": {
                    "type": "string"
                },
                "password": {
                    "type": "string"
                }
            }
        },
        "handler.RegisterRequest": {
            "type": "object",
            "required": [
                "email",
                "name",
                "password"
            ],
            "properties": {
                "email": {
                    "type": "string"
                },
                "name": {
                    "type": "string"
                },
                "password": {
                    "type": "string",
                    "minLength": 6
                }
            }
        },
        "handler.TopUpRequest": {
            "description": "Top up wallet balance (mock implementation)",
            "type": "object",
            "required": [
                "amount"
            ],
            "properties": {
                "amount": {
                    "type": "number"
                }
            }
        },
        "handler.TransferRequest": {
            "type": "object",
            "required": [
                "amount",
                "receiver_user_id"
            ],
            "properties": {
                "amount": {
                    "type": "number"
                },
                "receiver_user_id": {
                    "type": "integer"
                }
            }
        },
        "utils.ApiResponse": {
            "type": "object",
            "properties": {
                "code": {
                    "type": "integer"
                },
                "data": {},
                "error": {},
                "message": {
                    "type": "string"
                },
                "success": {
                    "type": "boolean"
                }
            }
        }
    },
    "securityDefinitions": {
        "BearerAuth": {
            "type": "apiKey",
            "name": "Authorization",
            "in": "header"
        }
    }
}